layer_linter/__init__.py
layer_linter/__main__.py
layer_linter/cmdline.py
layer_linter/contract.py
layer_linter/module.py
layer_linter/report.py
layer_linter/dependencies/__init__.py
layer_linter/dependencies/analysis.py
layer_linter/dependencies/graph.py
layer_linter/dependencies/path.py
layer_linter/dependencies/scanner.py
layer_linter-0.12.3.dist-info/AUTHORS.rst
layer_linter-0.12.3.dist-info/LICENSE
layer_linter-0.12.3.dist-info/METADATA
layer_linter-0.12.3.dist-info/WHEEL
layer_linter-0.12.3.dist-info/entry_points.txt
layer_linter-0.12.3.dist-info/top_level.txt
layer_linter-0.12.3.dist-info/RECORD
