Metadata-Version: 2.1
Name: layer-linter
Version: 0.12.3
Summary: Layer Linter checks that your project follows a custom-defined layered architecture.
Home-page: https://github.com/seddonym/layer_linter
Author: David Seddon
Author-email: david@seddonym.me
License: BSD license
Keywords: layer-linter layer-lint
Platform: UNKNOWN
Classifier: Development Status :: 7 - Inactive
Classifier: Intended Audience :: Developers
Classifier: License :: OSI Approved :: BSD License
Classifier: Natural Language :: English
Classifier: Programming Language :: Python :: 3
Classifier: Programming Language :: Python :: 3.6
Classifier: Programming Language :: Python :: 3.7
Requires-Dist: networkx (~=2.2)
Requires-Dist: PyYAML (~=4.2b1)
Requires-Dist: click (<8,>=6.7)
